{
  "display": {
    "icon": {
      "item": "minecraft:rotten_flesh"
    },
    "title": {
      "translate": "advancement.zombieapocalypseaddon.kill_250.title"
    },
    "description": {
      "translate": "advancement.zombieapocalypseaddon.kill_250.description"
    },
    "background": "minecraft:textures/gui/advancements/backgrounds/adventure.png",
    "frame": "task",
    "show_toast": true,
    "announce_to_chat": true,
    "hidden": false
  },
  "criteria": {
    "manual": {
      "trigger": "minecraft:impossible"
    }
  }
}
